my_awesome_package/__init__.py
my_awesome_package/main.py
my_awesome_package_laxman_2025-0.1.2.dist-info/licenses/LICENSE.txt
my_awesome_package_laxman_2025-0.1.2.dist-info/METADATA
my_awesome_package_laxman_2025-0.1.2.dist-info/WHEEL
my_awesome_package_laxman_2025-0.1.2.dist-info/top_level.txt
my_awesome_package_laxman_2025-0.1.2.dist-info/RECORD
