Metadata-Version: 2.4
Name: my-awesome-package-laxman-2025
Version: 0.1.2
Summary: A minimal, awesome Python package uploaded to PyPI.
Author-email: Laxman <your-email@example.com>
License: MIT License
Project-URL: Homepage, https://github.com/yourusername/my-awesome-package
Project-URL: Repository, https://github.com/yourusername/my-awesome-package
Classifier: Programming Language :: Python :: 3
Classifier: License :: OSI Approved :: MIT License
Classifier: Operating System :: OS Independent
Classifier: Development Status :: 3 - Alpha
Requires-Python: >=3.8
License-File: LICENSE.txt
Dynamic: license-file
